CHANGELOG.adoc
LICENSE
MANIFEST.in
README.md
setup.cfg
setup.py
bin/ssh-ldap-pubkey
bin/ssh-ldap-pubkey-wrapper
etc/ldap.conf
etc/openssh-lpk.schema
ssh_ldap_pubkey/__init__.py
ssh_ldap_pubkey/config.py
ssh_ldap_pubkey/exceptions.py
ssh_ldap_pubkey.egg-info/PKG-INFO
ssh_ldap_pubkey.egg-info/SOURCES.txt
ssh_ldap_pubkey.egg-info/dependency_links.txt
ssh_ldap_pubkey.egg-info/requires.txt
ssh_ldap_pubkey.egg-info/top_level.txt