Metadata-Version: 1.1
Name: ssh-ldap-pubkey
Version: 1.3.0
Summary: Utility to manage SSH public keys stored in LDAP.
Home-page: https://github.com/jirutka/ssh-ldap-pubkey
Author: Jakub Jirutka
Author-email: jakub@jirutka.cz
License: MIT
Platform: UNKNOWN
Classifier: Environment :: Console
Classifier: Intended Audience :: Developers
Classifier: License :: OSI Approved :: MIT License
Classifier: Operating System :: POSIX
Classifier: Programming Language :: Python :: 2
Classifier: Programming Language :: Python :: 3
Classifier: Topic :: System
Classifier: Topic :: Utilities
